LICENSE
README.md
setup.py
neurons/__init__.py
neurons/_base.py
neurons/application.py
neurons/context.py
neurons/model.py
neurons/version.py
neurons.egg-info/PKG-INFO
neurons.egg-info/SOURCES.txt
neurons.egg-info/dependency_links.txt
neurons.egg-info/not-zip-safe
neurons.egg-info/requires.txt
neurons.egg-info/top_level.txt
neurons/base/__init__.py
neurons/base/const.py
neurons/base/error.py
neurons/base/event.py
neurons/base/model.py
neurons/base/screen.py
neurons/base/service.py
neurons/base/session.py
neurons/daemon/__init__.py
neurons/daemon/cli.py
neurons/daemon/daemonize.py
neurons/daemon/ipc.py
neurons/daemon/main.py
neurons/daemon/store.py
neurons/daemon/config/__init__.py
neurons/daemon/config/_base.py
neurons/daemon/config/_wdict.py
neurons/daemon/config/daemon.py
neurons/daemon/config/endpoint.py
neurons/daemon/config/limits.py
neurons/daemon/config/logutils.py
neurons/daemon/config/static_file.py
neurons/daemon/config/store.py
neurons/daemon/test/__init__.py
neurons/daemon/test/test_config.py
neurons/form/__init__.py
neurons/form/form.py
neurons/form/table.py
neurons/form/widget.py
neurons/form/const/__init__.py
neurons/form/const/test.html
neurons/form/test/__init__.py
neurons/form/test/test_form.py
neurons/form/test/test_form_table.py
neurons/geojson/__init__.py
neurons/geojson/model.py
neurons/log/__init__.py
neurons/log/method_call.py
neurons/log/method_return.py
neurons/log/model.py
neurons/polymer/__init__.py
neurons/polymer/app.py
neurons/polymer/jsutil.py
neurons/polymer/model.py
neurons/polymer/service.py
neurons/polymer/const/__init__.py
neurons/polymer/const/defn.js
neurons/polymer/const/dom_module.html
neurons/polymer/const/preamble.js
neurons/polymer/const/screen.html
neurons/polymer/const/comp/__init__.py
neurons/polymer/const/comp/neurons-array/neurons-array.html
neurons/polymer/const/comp/neurons-complex-reference/neurons-complex-dropdown.html
neurons/polymer/const/comp/neurons-complex-reference/neurons-complex-href.html
neurons/polymer/const/comp/neurons-date-time/neurons-datetime-picker.html
neurons/polymer/const/comp/neurons-date-time/neurons-moment-validator.html
neurons/polymer/protocol/__init__.py
