Metadata-Version: 2.1
Name: neurons
Version: 0.10.0
Summary: Neurons is a web framework tying together Spyne, Twisted and SQLAlchemy.
Home-page: http://spyne.io/neurons
Author: Burak Arslan
Author-email: burak+neurons@arskom.com.tr
Maintainer: Burak Arslan
Maintainer-email: burak+neurons@arskom.com.tr
License: LGPL-2.1
Keywords: http
Classifier: Programming Language :: Python
Classifier: Programming Language :: Python :: 2
Classifier: Programming Language :: Python :: 2.7
Classifier: Programming Language :: Python :: 3
Classifier: Programming Language :: Python :: 3.3
Classifier: Programming Language :: Python :: 3.4
Classifier: Programming Language :: Python :: 3.5
Classifier: Programming Language :: Python :: 3.6
Classifier: Programming Language :: Python :: Implementation :: CPython
Classifier: Programming Language :: Python :: Implementation :: PyPy
Classifier: Operating System :: OS Independent
Classifier: Natural Language :: English
Classifier: Development Status :: 1 - Planning
Classifier: Intended Audience :: Developers
Classifier: Topic :: Internet :: WWW/HTTP :: Dynamic Content
License-File: LICENSE
